{
    "project_info": {
      "project_number": "210791468265",
      "firebase_url": "https://groceries-1e6eb.firebaseio.com",
      "project_id": "groceries-1e6eb",
      "storage_bucket": "groceries-1e6eb.appspot.com"
    },
    "client": [
      {
        "client_info": {
          "mobilesdk_app_id": "1:210791468265:android:e5f4ff4997c21e6d",
          "android_client_info": {
            "package_name": "org.nativescript.Groceries"
          }
        },
        "oauth_client": [
          {
            "client_id": "210791468265-dov54omf1amdtt50061mabsqic5ovu9q.apps.googleusercontent.com",
            "client_type": 3
          }
        ],
        "api_key": [
          {
            "current_key": "AIzaSyDE_s5l4wxzPyV5yOpn1EYreInvhb0_3Og"
          }
        ],
        "services": {
          "analytics_service": {
            "status": 1
          },
          "appinvite_service": {
            "status": 1,
            "other_platform_oauth_client": []
          },
          "ads_service": {
            "status": 2
          }
        }
      }
    ],
    "configuration_version": "1"
  }